pyrpkg/__init__.py
pyrpkg/cli.py
pyrpkg/completers.py
pyrpkg/errors.py
pyrpkg/gitignore.py
pyrpkg/lookaside.py
pyrpkg/man_gen.py
pyrpkg/sources.py
pyrpkg/spec.py
pyrpkg/utils.py
pyrpkg/layout/__init__.py
pyrpkg/layout/base.py
pyrpkg/layout/layouts.py
rpkg-1.68.dist-info/METADATA
rpkg-1.68.dist-info/WHEEL
rpkg-1.68.dist-info/licenses/COPYING
rpkg-1.68.dist-info/licenses/COPYING-koji
rpkg-1.68.dist-info/RECORD
