Metadata-Version: 2.4
Name: rpkg
Version: 1.68
Dynamic: License
Dynamic: License-Expression
Summary: A python library and runtime script for managing RPMpackage sources in a git repository
Project-URL: Homepage, https://pagure.io/rpkg
Author-email: Dennis Gilmore <ausil@fedoraproject.org>
License-File: COPYING
License-File: COPYING-koji
Classifier: Development Status :: 5 - Production/Stable
Classifier: Environment :: Console
Classifier: Intended Audience :: Developers
Classifier: License :: OSI Approved :: GNU General Public License v2 or later (GPLv2+)
Classifier: Natural Language :: English
Classifier: Operating System :: POSIX :: Linux
Classifier: Programming Language :: Python :: 2 :: Only
Classifier: Programming Language :: Python :: 2.7
Classifier: Programming Language :: Python :: 3
Classifier: Programming Language :: Python :: 3.6
Classifier: Programming Language :: Python :: 3.9
Classifier: Programming Language :: Python :: 3.12
Classifier: Programming Language :: Python :: 3.13
Classifier: Topic :: Software Development :: Build Tools
Classifier: Topic :: Software Development :: Libraries :: Python Modules
Requires-Dist: argcomplete
Requires-Dist: cccolutils>=1.4
Requires-Dist: gitpython
Requires-Dist: koji>=1.15
Requires-Dist: pycurl
Requires-Dist: pyyaml
Requires-Dist: requests
Requires-Dist: rpm
Requires-Dist: six>=1.9.0
